{
  "company": {
    "name": "Nuestra Panadería",
    "logo": "/assets/images/logo.png"
  },
  "navigation": [
    {
      "name": "Sobre Nosotros",
      "href": "product"
    },
    {
      "name": "Contáctanos",
      "href": "features"
    }
  ],
  "callToAction": {
    "text": "Get started",
    "href": "#"
  },
  "mainHero": {
    "title": "Meridiano20 ",
    "subtitle": "",
    "description": "Participación Ciudadana en Acción ",
    "img": "/assets/images/1.png",
    "primaryAction": {
      "text": "Get started",
      "href": "#"
    },
    "secondaryAction": {
      "text": "Email us",
      "href": "mailto:issaafakattan@gmail.com?subject=I like react landing page!"
    }
  },
  "product": {
    "title": "Sobre Nosotros",
    "items": [
      {
        "title": "Lo que creemos",
        "description": "Meridiano20 es tu fuente confiable de noticias y publicidad, enfocada en fomentar la participación ciudadana. Nos dedicamos a informar y conectar a la comunidad, brindando un espacio para que las voces locales sean escuchadas y las acciones positivas sean destacadas.",
        "img": "/assets/images/2.png"
      },
      {
        "title": "Nuestra misión",
        "description": "A través de nuestra plataforma, promovemos la interacción y el diálogo, contribuyendo a una sociedad más informada y comprometida.",
        "img": "/assets/images/3.png"
      }
    ]
  },
  "features": {
    "title": "¡Contáctanos! ",
    "subtitle": "¡Estamos aquí para ayudarte!",
    "description": "Si necesitas más información o quieres contratar alguno de nuestros servicios, no dudes en contactarnos. Estamos disponibles para resolver tus dudas y brindarte la mejor atención.",
    "items": [
      {
        "name": "Número",
        "description": "+57 320 2648649",
        "icon": "/assets/images/phone.png"
      },
      {
        "name": "Blog",
        "description": "https://www.meridiano20.com.co/",
        "icon": "/assets/images/blog.png",
        "url":"https://www.meridiano20.com.co/"
      },
      {
        "name": "Facebook",
        "description": "MERIDIANO 20",
        "icon": "/assets/images/facebook.jpg",
        "url":"https://www.facebook.com/meridiano20"
      },
      {
        "name": "Twitter",
        "description": "@Meridiano20h",
        "icon": "/assets/images/x.png",
        "url":"https://twitter.com/Meridiano20h"
      },
      {
        "name": "Youtube",
        "description": "Meridiano20comco",
        "icon": "/assets/images/youtube.png",
        "url":"https://www.youtube.com/meridiano20comco"
      }
    ]
  },
  "pricing": {
    "title": "Pricing",
    "items": [
      {
        "name": "Free",
        "price": "$0",
        "priceDetails": "for one user",
        "features": [
          "1 user",
          "Basic Support",
          "1 GB of storage",
          "Email support"
        ]
      },
      {
        "name": "Pro",
        "price": "$15",
        "priceDetails": "per user",

        "features": [
          "5 users",
          "Priority Support",
          "10 GB of storage",
          "Phone and Email support"
        ]
      },
      {
        "name": "Enterprise",
        "price": "$29",
        "priceDetails": "per user",
        "features": [
          "50 users",
          "24/7 Support",
          "100 GB of storage",
          "Phone and Email support"
        ]
      }
    ]
  },
  "about": {
    "sections": [
      {
        "name": "Something",
        "href": "#",
        "content": "It is a long established fact that a reader will be distracted by the readable content of a page when looking at its layout. The point of using Lorem Ipsum is that it has a more-or-less normal distribution of letters, as opposed to using 'Content here, content here', making it look like readable English."
      },
      {
        "name": "Something",
        "href": "#",
        "content": "It is a long established fact that a reader will be distracted by the readable content of a page when looking at its layout. The point of using Lorem Ipsum is that it has a more-or-less normal distribution of letters, as opposed to using 'Content here, content here', making it look like readable English."
      },
      {
        "name": "Something",
        "href": "#",
        "content": "It is a long established fact that a reader will be distracted by the readable content of a page when looking at its layout. The point of using Lorem Ipsum is that it has a more-or-less normal distribution of letters, as opposed to using 'Content here, content here', making it look like readable English."
      },
      {
        "name": "Something",
        "href": "#",
        "content": "It is a long established fact that a reader will be distracted by the readable content of a page when looking at its layout. The point of using Lorem Ipsum is that it has a more-or-less normal distribution of letters, as opposed to using 'Content here, content here', making it look like readable English."
      }
    ],
    "socialMedia": {
      "github": "https://github.com/",
      "twitter": "https://twitter.com/",
      "linkedin": "https://www.linkedin.com/in/"
    }
  }
}
